firerequests/VERSION
firerequests/__init__.py
firerequests/main.py
firerequests/version.py
firerequests-0.1.4.dist-info/licenses/LICENSE
firerequests-0.1.4.dist-info/METADATA
firerequests-0.1.4.dist-info/WHEEL
firerequests-0.1.4.dist-info/entry_points.txt
firerequests-0.1.4.dist-info/top_level.txt
firerequests-0.1.4.dist-info/RECORD
