Metadata-Version: 2.4
Name: firerequests
Version: 0.1.4
Summary: High-Performance Asynchronous HTTP Client setting Requests on Fire 🔥
Home-page: https://github.com/rishiraj/firerequests
Author: Rishiraj Acharya
Author-email: heyrishiraj@gmail.com
Classifier: Programming Language :: Python :: 3
Classifier: License :: OSI Approved :: Apache Software License
Classifier: Operating System :: OS Independent
Requires-Python: >=3.8
License-File: LICENSE
Requires-Dist: aiohttp
Requires-Dist: aiofiles
Requires-Dist: requests
Requires-Dist: nest_asyncio
Requires-Dist: tqdm
Requires-Dist: fire
Dynamic: author
Dynamic: author-email
Dynamic: classifier
Dynamic: description
Dynamic: description-content-type
Dynamic: home-page
Dynamic: license-file
Dynamic: requires-dist
Dynamic: requires-python
Dynamic: summary
